sopp/__about__.py
sopp/__init__.py
sopp/generate_tardys3.py
sopp/sopp.py
sopp/tardys4_generator.py
sopp/utilities.py
sopp/window_finder.py
sopp/builder/configuration_builder.py
sopp/config_file_loader/__init__.py
sopp/config_file_loader/config_file_loader_factory.py
sopp/config_file_loader/support/__init__.py
sopp/config_file_loader/support/config_file_loader_base.py
sopp/config_file_loader/support/config_file_loader_json.py
sopp/config_file_loader/support/utilities.py
sopp/custom_dataclasses/__init__.py
sopp/custom_dataclasses/configuration.py
sopp/custom_dataclasses/configuration_file.py
sopp/custom_dataclasses/coordinates.py
sopp/custom_dataclasses/facility.py
sopp/custom_dataclasses/observation_target.py
sopp/custom_dataclasses/overhead_window.py
sopp/custom_dataclasses/position.py
sopp/custom_dataclasses/position_time.py
sopp/custom_dataclasses/reservation.py
sopp/custom_dataclasses/runtime_settings.py
sopp/custom_dataclasses/time_window.py
sopp/custom_dataclasses/frequency_range/__init__.py
sopp/custom_dataclasses/frequency_range/frequency_range.py
sopp/custom_dataclasses/frequency_range/support/__init__.py
sopp/custom_dataclasses/frequency_range/support/get_frequency_data_from_csv.py
sopp/custom_dataclasses/satellite/__init__.py
sopp/custom_dataclasses/satellite/international_designator.py
sopp/custom_dataclasses/satellite/mean_motion.py
sopp/custom_dataclasses/satellite/satellite.py
sopp/custom_dataclasses/satellite/tle_information.py
sopp/event_finder/__init__.py
sopp/event_finder/event_finder.py
sopp/event_finder/event_finder_rhodesmill/__init__.py
sopp/event_finder/event_finder_rhodesmill/event_finder_rhodesmill.py
sopp/event_finder/event_finder_rhodesmill/support/evenly_spaced_time_intervals_calculator.py
sopp/event_finder/event_finder_rhodesmill/support/satellites_interference_filter.py
sopp/event_finder/event_finder_rhodesmill/support/satellite_positions_with_respect_to_facility_retriever/__init__.py
sopp-0.8.1.dist-info/METADATA
sopp-0.8.1.dist-info/WHEEL
sopp-0.8.1.dist-info/licenses/COPYING
sopp-0.8.1.dist-info/RECORD
