Metadata-Version: 2.3
Name: sopp
Version: 0.8.1
Summary: SOPP is an open-source tool for calculating satellite interference to radio astronomy observations.
Project-URL: Repository, https://github.com/NSF-Swift/satellite-overhead
Project-URL: Bug Tracker, https://github.com/NSF-Swift/satellite-overhead/issues
License-Expression: AGPL-3.0-or-later
License-File: COPYING
Keywords: astronomy,satellites
Classifier: Development Status :: 3 - Alpha
Classifier: License :: OSI Approved :: GNU Affero General Public License v3 or later (AGPLv3+)
Classifier: Programming Language :: Python :: 3.9
Classifier: Programming Language :: Python :: 3.10
Requires-Python: >=3.8
Requires-Dist: python-dateutil~=2.8.2
Requires-Dist: python-dotenv~=0.21.0
Requires-Dist: requests~=2.31.0
Requires-Dist: sgp4~=2.21
Requires-Dist: skyfield~=1.47
